setup.py
adp_userinfo/__init__.py
adp_userinfo/version.py
adp_userinfo.egg-info/PKG-INFO
adp_userinfo.egg-info/SOURCES.txt
adp_userinfo.egg-info/dependency_links.txt
adp_userinfo.egg-info/entry_points.txt
adp_userinfo.egg-info/requires.txt
adp_userinfo.egg-info/top_level.txt
adp_userinfo/lib/__init__.py
adp_userinfo/lib/userInfoHelper.py
adp_userinfo/lib/userinfoexceptions.py
adp_userinfo/lib/userinfourlmap.py
tests/__init__.py
tests/base.py
tests/test_userinfo.py
tests/test_version.py