Metadata-Version: 1.1
Name: adp-userinfo
Version: 1.0
Summary: ADP client library to get the logged-in users info
Home-page: https://github.com/adplabs/adp-userinfo-python
Author: Copyright © 2015-2016 ADP, LLC.
Author-email: Vishal.Shah-Contractor@adp.com
License: Apache Software License
Keywords: ADP userinfo
Platform: UNKNOWN
Classifier: Development Status :: 4 - Beta
Classifier: Intended Audience :: Developers
Classifier: License :: OSI Approved :: Apache Software License
Classifier: Natural Language :: English
Classifier: Operating System :: Unix
Classifier: Programming Language :: Python :: 2.7
Classifier: Operating System :: OS Independent
